BTKSorgu/__init__.py
BTKSorgu/arayuz.py
BTKSorgu/konsol.py
BTKSorgu/Assets/logo.png
BTKSorgu/Core/__init__.py
BTKSorgu/GUI/__init__.py
BTKSorgu/Libs/__init__.py
BTKSorgu-1.3.6.data/data/share/appdata/org.KekikAkademi.BTKSorgu.appdata.xml
BTKSorgu-1.3.6.data/data/share/applications/org.KekikAkademi.BTKSorgu.desktop
BTKSorgu-1.3.6.data/data/share/icons/hicolor/scalable/apps/org.KekikAkademi.BTKSorgu.svg
BTKSorgu-1.3.6.dist-info/LICENSE
BTKSorgu-1.3.6.dist-info/METADATA
BTKSorgu-1.3.6.dist-info/WHEEL
BTKSorgu-1.3.6.dist-info/entry_points.txt
BTKSorgu-1.3.6.dist-info/top_level.txt
BTKSorgu-1.3.6.dist-info/RECORD
