Metadata-Version: 2.1
Name: BTKSorgu
Version: 1.3.6
Summary: Hedef websitesinin BTK Tarafından Erişim Engeli Sorgusu
Home-page: https://github.com/keyiflerolsun/BTKSorgu
Author: keyiflerolsun
Author-email: keyiflerolsun@gmail.com
License: GPLv3+
Keywords: BTKSorgu,KekikAkademi,keyiflerolsun
Classifier: Development Status :: 5 - Production/Stable
Classifier: License :: OSI Approved :: GNU General Public License v3 or later (GPLv3+)
Classifier: Programming Language :: Python :: 3
Requires-Python: >=3.10
License-File: LICENSE
Requires-Dist: setuptools
Requires-Dist: wheel
Requires-Dist: install-freedesktop
Requires-Dist: rich
Requires-Dist: requests
Requires-Dist: parsel
Requires-Dist: cssselect
Requires-Dist: regex
Requires-Dist: Pillow
Requires-Dist: pytesseract
Requires-Dist: sv-ttk
